[{"year": 2019, "value": 1.35}, {"year": 2020, "value": 0.8}, {"year": 2021, "value": 0.96}, {"year": 2019, "value": 0.44}, {"year": 2020, "value": 0.35}, {"year": 2021, "value": 0.34}, {"year": 2019, "value": 0.31}, {"year": 2020, "value": 0.22}, {"year": 2021, "value": 0.28}, {"year": 2019, "value": 0.13}, {"year": 2020, "value": 0.13}, {"year": 2021, "value": 0.06}, {"year": 2019, "value": 0.01}, {"year": 2020, "value": 0.0}, {"year": 2021, "value": 0.0}, {"year": 2019, "value": 0.52}, {"year": 2020, "value": 0.2}, {"year": 2021, "value": 0.35}, {"year": 2019, "value": 0.17}, {"year": 2020, "value": 0.11}, {"year": 2021, "value": 0.13}, {"year": 2019, "value": 0.1}, {"year": 2020, "value": 0.03}, {"year": 2021, "value": 0.03}, {"year": 2019, "value": 0.12}, {"year": 2020, "value": 0.11}, {"year": 2021, "value": 0.11}]