[{"year": 2019, "value": 6.43}, {"year": 2020, "value": 6.65}, {"year": 2021, "value": 7.16}, {"year": 2019, "value": 2.62}, {"year": 2020, "value": 2.69}, {"year": 2021, "value": 3.29}, {"year": 2020, "value": 2.69}, {"year": 2021, "value": 3.29}, {"year": 2020, "value": 0.0}, {"year": 2019, "value": 0.12}, {"year": 2020, "value": 0.08}, {"year": 2021, "value": 0.09}, {"year": 2019, "value": 0.95}, {"year": 2020, "value": 0.89}, {"year": 2021, "value": 0.76}, {"year": 2019, "value": 0.45}, {"year": 2020, "value": 0.38}, {"year": 2021, "value": 0.42}, {"year": 2019, "value": 0.98}, {"year": 2020, "value": 0.96}, {"year": 2021, "value": 0.99}, {"year": 2019, "value": 1.32}, {"year": 2020, "value": 1.64}, {"year": 2021, "value": 1.61}]