[{"year": 2005, "value": 763.0}, {"year": 2006, "value": 11342.0}, {"year": 2007, "value": 31406.0}, {"year": 2008, "value": 47142.0}, {"year": 2009, "value": 66106.0}, {"year": 2010, "value": 46527.0}, {"year": 2011, "value": 42360.0}, {"year": 2012, "value": 37235.0}, {"year": 2013, "value": 38268.0}, {"year": 2014, "value": 45420.0}, {"year": 2015, "value": 49008.0}, {"year": 2016, "value": 53715.0}, {"year": 2017, "value": 55831.0}, {"year": 2018, "value": 58040.0}, {"year": 2019, "value": 64730.0}, {"year": 2020, "value": 60863.0}, {"year": 2021, "value": 63185.0}, {"year": 2019, "value": 30112.0}, {"year": 2020, "value": 28525.0}, {"year": 2021, "value": 30990.0}, {"year": 2019, "value": 30112.0}, {"year": 2020, "value": 28525.0}, {"year": 2021, "value": 30935.0}, {"year": 2020, "value": 0.0}, {"year": 2021, "value": 55.0}, {"year": 2019, "value": 515.0}, {"year": 2020, "value": 473.0}, {"year": 2021, "value": 475.0}, {"year": 2019, "value": 7532.0}, {"year": 2020, "value": 6452.0}, {"year": 2021, "value": 5710.0}, {"year": 2019, "value": 3106.0}, {"year": 2020, "value": 3155.0}, {"year": 2021, "value": 3116.0}, {"year": 2019, "value": 7704.0}, {"year": 2020, "value": 6922.0}, {"year": 2021, "value": 6142.0}, {"year": 2019, "value": 15762.0}, {"year": 2020, "value": 15337.0}, {"year": 2021, "value": 16752.0}]