[{"year": 2019, "value": 7.15}, {"year": 2020, "value": 7.47}, {"year": 2021, "value": 6.93}, {"year": 2019, "value": 3.76}, {"year": 2020, "value": 3.92}, {"year": 2021, "value": 3.88}, {"year": 2020, "value": 3.92}, {"year": 2021, "value": 3.88}, {"year": 2021, "value": 0.0}, {"year": 2019, "value": 0.08}, {"year": 2020, "value": 0.08}, {"year": 2021, "value": 0.08}, {"year": 2019, "value": 1.34}, {"year": 2020, "value": 1.42}, {"year": 2021, "value": 1.23}, {"year": 2019, "value": 0.54}, {"year": 2020, "value": 0.65}, {"year": 2021, "value": 0.48}, {"year": 2019, "value": 0.82}, {"year": 2020, "value": 0.88}, {"year": 2021, "value": 0.76}, {"year": 2019, "value": 0.61}, {"year": 2020, "value": 0.51}, {"year": 2021, "value": 0.5}]