[{"year": 2019, "value": 86.5}, {"year": 2020, "value": 95.5}, {"year": 2021, "value": 85.1}, {"year": 2019, "value": 95.7}, {"year": 2020, "value": 95.7}, {"year": 2021, "value": 94.9}, {"year": 2019, "value": 79.2}, {"year": 2020, "value": 85.3}, {"year": 2021, "value": 79.8}, {"year": 2019, "value": 81.4}, {"year": 2020, "value": 89.6}, {"year": 2021, "value": 77.3}, {"year": 2019, "value": 92.0}, {"year": 2020, "value": 82.0}, {"year": 2021, "value": 93.2}, {"year": 2019, "value": 83.0}, {"year": 2020, "value": 95.2}, {"year": 2021, "value": 85.8}]