[{"year": 2005, "value": 48531.0}, {"year": 2006, "value": 51523.0}, {"year": 2007, "value": 56022.0}, {"year": 2008, "value": 60656.0}, {"year": 2009, "value": 45465.0}, {"year": 2010, "value": 49252.0}, {"year": 2011, "value": 46060.0}, {"year": 2012, "value": 47886.0}, {"year": 2013, "value": 46080.0}, {"year": 2014, "value": 53311.0}, {"year": 2015, "value": 52701.0}, {"year": 2016, "value": 65837.0}, {"year": 2017, "value": 68277.0}, {"year": 2018, "value": 73861.0}, {"year": 2019, "value": 198282.0}, {"year": 2020, "value": 209813.0}, {"year": 2021, "value": 221386.0}]